LICENSE.txt
MANIFEST.in
README.md
setup.cfg
setup.py
google_chat_handler/__init__.py
google_chat_handler.egg-info/PKG-INFO
google_chat_handler.egg-info/SOURCES.txt
google_chat_handler.egg-info/dependency_links.txt
google_chat_handler.egg-info/requires.txt
google_chat_handler.egg-info/top_level.txt
google_chat_handler.egg-info/zip-safe