Metadata-Version: 2.1
Name: google-chat-handler
Version: 1.0.0
Summary: Log data in google chat
Home-page: https://github.com/anandtripathi5/google-chat-handler.git
Author: Anand Tripathi
Author-email: anand.tripathi507@gmail.com
License: UNKNOWN
Keywords: Google Chat Handler,google chat logging
Platform: UNKNOWN
